LICENSE
MANIFEST.in
README.md
setup.cfg
setup.py
sphinxfolders/__init__.py
sphinxfolders/directives.py
sphinxfolders/nodes.py
sphinxfolders/visitors.py
sphinxfolders.egg-info/PKG-INFO
sphinxfolders.egg-info/SOURCES.txt
sphinxfolders.egg-info/dependency_links.txt
sphinxfolders.egg-info/not-zip-safe
sphinxfolders.egg-info/requires.txt
sphinxfolders.egg-info/top_level.txt