Metadata-Version: 1.0
Name: sphinxfolders
Version: 1.0.3
Summary: Sphinx directive to list the content of a folder
Home-page: https://github.com/d9pouces/SphinxFolders/
Author: Matthieu Gallet
Author-email: github@19pouces.net
License: CeCILL-B
Platform: UNKNOWN
